{
  "title": "Nikkei reverses course as tech stocks track Wall Street's gains - Reuters",
  "url": "https://www.reuters.com/markets/europe/nikkei-reverses-course-tech-stocks-track-wall-streets-gains-2022-01-31/",
  "date": "Mon, 31 Jan 2022 02:40:00 GMT",
  "content": "<a href=\"https://www.reuters.com/markets/europe/nikkei-reverses-course-tech-stocks-track-wall-streets-gains-2022-01-31/\" target=\"_blank\">Nikkei reverses course as tech stocks track Wall Street's gains</a>&nbsp;&nbsp;<font color=\"#6f6f6f\">Reuters</font>",
  "image": "https://www.reuters.com/pf/resources/images/reuters/reuters-default.png?d=69",
  "description": "Japan's Nikkei index reversed course to trade higher on Monday, with technology heavyweights leading the gains, as risk sentiment was lifted by Wall Street's strong finish.",
  "publisher": "Google News Tech USA",
  "publisherUrl": "https://news.google.com/topstories?hl=en-US&gl=US&ceid=US:en"
}